lts_scan/__init__.py
lts_scan/cli.py
lts_scan/scanner.py
lts_scan-0.1.5.dist-info/LICENSE
lts_scan-0.1.5.dist-info/METADATA
lts_scan-0.1.5.dist-info/WHEEL
lts_scan-0.1.5.dist-info/entry_points.txt
lts_scan-0.1.5.dist-info/RECORD
