Metadata-Version: 2.3
Name: lts-scan
Version: 0.1.5
Summary: Lightweight TLS Scanner using SSL Labs API
License: MIT
Keywords: tls,ssl,scanner,ssllabs,security
Author: Alexandre Meline
Author-email: alexandre.meline.dev@gmail.com
Requires-Python: >=3.10,<4.0
Classifier: License :: OSI Approved :: MIT License
Classifier: Operating System :: OS Independent
Classifier: Programming Language :: Python :: 3
Classifier: Programming Language :: Python :: 3.10
Classifier: Programming Language :: Python :: 3.11
Classifier: Programming Language :: Python :: 3.12
Classifier: Programming Language :: Python :: 3.13
Requires-Dist: aiohttp (>=3.11.16,<4.0.0)
Project-URL: Repository, https://github.com/alexandre-meline/LTS_scan
